gitstatic/__init__.py
gitstatic-0.0.1.dist-info/LICENSE
gitstatic-0.0.1.dist-info/METADATA
gitstatic-0.0.1.dist-info/WHEEL
gitstatic-0.0.1.dist-info/top_level.txt
gitstatic-0.0.1.dist-info/RECORD
